sdcensus/__init__.py
sdcensus/core.py
sdcensus/tests/__init__.py
sdcensus/tests/test_census.py
sdcensus-0.8.31.dist-info/LICENSE
sdcensus-0.8.31.dist-info/METADATA
sdcensus-0.8.31.dist-info/WHEEL
sdcensus-0.8.31.dist-info/top_level.txt
sdcensus-0.8.31.dist-info/RECORD
