Metadata-Version: 2.1
Name: sdcensus
Version: 0.8.31
Summary: A wrapper for the US Census Bureau's API
Home-page: http://github.com/datamade/census
Author: Jeremy Carbaugh
Author-email: jcarbaugh@sunlightfoundation.com
Maintainer: Forest Gregg
Maintainer-email: fgregg@gmail.com
License: BSD
Platform: any
Classifier: Development Status :: 4 - Beta
Classifier: Intended Audience :: Developers
Classifier: License :: OSI Approved :: BSD License
Classifier: Natural Language :: English
Classifier: Operating System :: OS Independent
Classifier: Programming Language :: Python
License-File: LICENSE
Requires-Dist: requests>=1.1.0
